praicing/__init__.py
praicing/openai.py
praicing/py.typed
praicing-0.0.3.dist-info/METADATA
praicing-0.0.3.dist-info/WHEEL
praicing-0.0.3.dist-info/licenses/LICENSE
praicing-0.0.3.dist-info/RECORD
