Metadata-Version: 2.4
Name: praicing
Version: 0.0.3
Summary: Offline utility functions for estimating costs across different model providers.
Project-URL: Issues, https://github.com/joaopalmeiro/praicing/issues
Project-URL: Source, https://github.com/joaopalmeiro/praicing
Author-email: João Palmeiro <joaopalmeiro@proton.me>
License-Expression: MIT
License-File: LICENSE
Classifier: Development Status :: 4 - Beta
Classifier: Intended Audience :: Developers
Classifier: License :: OSI Approved :: MIT License
Classifier: Natural Language :: English
Classifier: Operating System :: OS Independent
Classifier: Programming Language :: Python
Classifier: Programming Language :: Python :: 3
Classifier: Programming Language :: Python :: 3 :: Only
Classifier: Programming Language :: Python :: 3.10
Classifier: Programming Language :: Python :: 3.11
Classifier: Programming Language :: Python :: 3.12
Classifier: Programming Language :: Python :: 3.13
Classifier: Programming Language :: Python :: Implementation :: CPython
Classifier: Topic :: Utilities
Classifier: Typing :: Typed
Requires-Python: >=3.10
Requires-Dist: openai>=1.97.0
Requires-Dist: pillow>=11.0.0
Requires-Dist: tiktoken>=0.9.0
